[
    {
        "type": "text",
        "text": "一、Vision Basic",
        "text_level": 1,
        "bbox": [
            67,
            111,
            329,
            136
        ],
        "page_idx": 0
    },
    {
        "type": "text",
        "text": "1.相机基础知识：",
        "text_level": 1,
        "bbox": [
            67,
            229,
            268,
            253
        ],
        "page_idx": 0
    },
    {
        "type": "text",
        "text": "分辨率（Resolution)：相机采集图像的像素点数",
        "bbox": [
            65,
            294,
            438,
            311
        ],
        "page_idx": 0
    },
    {
        "type": "text",
        "text": "像素分辨率（mm/pixel)：每个像素代表的毫米值",
        "bbox": [
            65,
            313,
            447,
            329
        ],
        "page_idx": 0
    },
    {
        "type": "text",
        "text": "快门方式：",
        "bbox": [
            67,
            332,
            149,
            348
        ],
        "page_idx": 0
    },
    {
        "type": "text",
        "text": "全局快门/全域快门(Global Shutter)：让整个感光元器件每行像素全部在同一时间进行曝光，也就是所有像元同时曝光。全局快门曝光时间更短，这样不仅能提升效率，也能根除影像果冻现象。",
        "bbox": [
            65,
            350,
            927,
            385
        ],
        "page_idx": 0
    },
    {
        "type": "text",
        "text": "滚动快门(Rolling Shutter)：感光元件是从第一行、第二行、第三行... 这样按照顺序进行光线感测，一直到整片感光组件从上到下每一行都曝光完成为止。卷帘快门曝光时间更长，另外就是在拍照的时候，假如工业相机有晃动，或者拍摄快速移动的物体，就会看到画面上的果冻现象。",
        "bbox": [
            65,
            388,
            929,
            441
        ],
        "page_idx": 0
    },
    {
        "type": "text",
        "text": "成像质量：受 视野大小、镜头焦距、镜头光圈、光源的类型、光源的安装位置、曝光时间、物距、CCD成像器类型、工作距离、景深等的影响。",
        "bbox": [
            65,
            443,
            929,
            478
        ],
        "page_idx": 0
    },
    {
        "type": "text",
        "text": "2.镜头基础知识：",
        "text_level": 1,
        "bbox": [
            65,
            502,
            268,
            525
        ],
        "page_idx": 0
    },
    {
        "type": "text",
        "text": "$\\textcircled{1}$ 镜头类型：",
        "text_level": 1,
        "bbox": [
            68,
            575,
            233,
            598
        ],
        "page_idx": 0
    },
    {
        "type": "text",
        "text": "广角镜头：焦距小于标准焦距 50mm 的。例如：16mm",
        "bbox": [
            65,
            640,
            489,
            656
        ],
        "page_idx": 0
    },
    {
        "type": "text",
        "text": "景深大，聚焦距离更近 ",
        "bbox": [
            68,
            659,
            248,
            674
        ],
        "page_idx": 0
    },
    {
        "type": "text",
        "text": "远距照像镜头：焦距大于标准焦距 50mm 的。例如：75mm",
        "bbox": [
            68,
            677,
            524,
            693
        ],
        "page_idx": 0
    },
    {
        "type": "text",
        "text": "景深浅，放大远距离物体",
        "bbox": [
            68,
            696,
            265,
            712
        ],
        "page_idx": 0
    },
    {
        "type": "text",
        "text": "变焦镜头：镜头焦距可调节，焦距有范围，例如：35-70mm",
        "bbox": [
            68,
            714,
            529,
            730
        ],
        "page_idx": 0
    },
    {
        "type": "text",
        "text": "定焦镜头：镜头焦距不可调节。例如： $2 5 \\mathsf { m m }$ ",
        "bbox": [
            68,
            733,
            418,
            747
        ],
        "page_idx": 0
    },
    {
        "type": "text",
        "text": "远心镜头：没有透视形变 即普通镜头导致的近大远小现象",
        "bbox": [
            68,
            751,
            515,
            766
        ],
        "page_idx": 0
    },
    {
        "type": "text",
        "text": "畸变类型：包括径向畸变和切向畸变",
        "bbox": [
            68,
            770,
            354,
            785
        ],
        "page_idx": 0
    },
    {
        "type": "text",
        "text": "径向畸变：桶形畸变，枕形畸变 ",
        "bbox": [
            68,
            788,
            319,
            804
        ],
        "page_idx": 0
    },
    {
        "type": "text",
        "text": "切向畸变：镜头不完全平行于相机传感器产生的畸变",
        "bbox": [
            68,
            807,
            477,
            822
        ],
        "page_idx": 0
    },
    {
        "type": "text",
        "text": "远心镜头：",
        "bbox": [
            68,
            825,
            149,
            841
        ],
        "page_idx": 0
    },
    {
        "type": "text",
        "text": "优势：超低畸变、高分辨率、 超宽景深",
        "bbox": [
            68,
            844,
            374,
            860
        ],
        "page_idx": 0
    },
    {
        "type": "text",
        "text": "放大倍率：CCD/FOV=倍率",
        "bbox": [
            68,
            863,
            268,
            878
        ],
        "page_idx": 0
    },
    {
        "type": "text",
        "text": "普通镜头和远心镜头：",
        "bbox": [
            68,
            881,
            238,
            897
        ],
        "page_idx": 0
    },
    {
        "type": "image",
        "img_path": "images/718240ed33b0fe258d3389e0aa8d6948cd5884301ec949c9e6923551e60f9a09.jpg",
        "image_caption": [],
        "image_footnote": [],
        "bbox": [
            70,
            53,
            378,
            190
        ],
        "page_idx": 1
    },
    {
        "type": "image",
        "img_path": "images/0506d8a2007ed7d444932c843b9480ce6bd5d4b1934ac368d65c8d2f304da1b3.jpg",
        "image_caption": [],
        "image_footnote": [],
        "bbox": [
            379,
            67,
            749,
            166
        ],
        "page_idx": 1
    },
    {
        "type": "text",
        "text": "$\\textcircled{2}$ 镜头参数：",
        "text_level": 1,
        "bbox": [
            70,
            225,
            231,
            249
        ],
        "page_idx": 1
    },
    {
        "type": "text",
        "text": "光圈：光圈是一个用来控制镜头通光量的装置 ，表示光圈大小我们是用光圈值（F值） ，如F1.4，F2，F2.8",
        "bbox": [
            65,
            292,
            895,
            307
        ],
        "page_idx": 1
    },
    {
        "type": "text",
        "text": "焦距（Focus）：透镜中心到其焦点的距离",
        "bbox": [
            68,
            311,
            394,
            325
        ],
        "page_idx": 1
    },
    {
        "type": "text",
        "text": "景深（DOF）：被测物体清晰成像的最上表面与最下表面之间的距离",
        "bbox": [
            67,
            329,
            596,
            344
        ],
        "page_idx": 1
    },
    {
        "type": "text",
        "text": "光圈和景深的关系：",
        "bbox": [
            68,
            348,
            220,
            362
        ],
        "page_idx": 1
    },
    {
        "type": "image",
        "img_path": "images/f3db6cd6b7ababec8d3a9654cff3f2b9e31b5aeec4fe5ddb619df9f0c4d3dca5.jpg",
        "image_caption": [
            "光圈越大-景深越小，光圈越小-景深越大"
        ],
        "image_footnote": [],
        "bbox": [
            72,
            366,
            410,
            481
        ],
        "page_idx": 1
    },
    {
        "type": "text",
        "text": "3.光源：",
        "text_level": 1,
        "bbox": [
            65,
            536,
            159,
            558
        ],
        "page_idx": 1
    },
    {
        "type": "text",
        "text": "光源的选择：光源可以做成各种形状，光源的安装角度和安装方向直接决定图象的效果。",
        "bbox": [
            65,
            602,
            747,
            618
        ],
        "page_idx": 1
    },
    {
        "type": "text",
        "text": "改变图像采集亮度的方式有：调整光源亮度、调整光圈值，调整曝光时间，更换大像元相机",
        "bbox": [
            65,
            620,
            776,
            636
        ],
        "page_idx": 1
    },
    {
        "type": "text",
        "text": "偏振光：用于减少眩光或者是镜面反射 ",
        "bbox": [
            65,
            639,
            371,
            653
        ],
        "page_idx": 1
    },
    {
        "type": "text",
        "text": "低角度光：主要用于边缘有倒角、圆角物体轮廓提取、冲压、浇筑、浮雕图案识别与检测，光滑表面划伤、裂痕检测。",
        "bbox": [
            65,
            658,
            924,
            690
        ],
        "page_idx": 1
    },
    {
        "type": "text",
        "text": "缺点：对于透明物体表面的划痕检测效果不理想效果不理想",
        "bbox": [
            65,
            695,
            534,
            709
        ],
        "page_idx": 1
    },
    {
        "type": "text",
        "text": "高角度光：主要用于表面粗糙程度不同区域的区分、边缘或内部有垂直断差或者比较陡峭（超过 60度）边缘检测或测量。",
        "bbox": [
            65,
            713,
            927,
            746
        ],
        "page_idx": 1
    },
    {
        "type": "text",
        "text": "缺点：对于反光区域相差不大的效果不理想",
        "bbox": [
            65,
            750,
            411,
            765
        ],
        "page_idx": 1
    },
    {
        "type": "text",
        "text": "同轴光：含有 $\\cdot$ 度银镜。同轴光源能够凸显物体表面不平整，克服表面反光造成的干扰，主要用于检测物体平整光滑表面的碰伤、划伤、裂纹和异物。",
        "bbox": [
            65,
            769,
            927,
            802
        ],
        "page_idx": 1
    },
    {
        "type": "text",
        "text": "背光：用于轮廓和边缘检测；用于透明物体内不透明物体的检测。",
        "bbox": [
            65,
            806,
            571,
            821
        ],
        "page_idx": 1
    },
    {
        "type": "text",
        "text": "非同轴漫射光应用及光路图：可以避免因弯曲表面导致的打光不均匀",
        "bbox": [
            65,
            825,
            600,
            840
        ],
        "page_idx": 1
    },
    {
        "type": "text",
        "text": "彩色光源：",
        "text_level": 1,
        "bbox": [
            65,
            862,
            149,
            876
        ],
        "page_idx": 1
    },
    {
        "type": "text",
        "text": "相近色和互补色：",
        "text_level": 1,
        "bbox": [
            65,
            879,
            201,
            895
        ],
        "page_idx": 1
    },
    {
        "type": "text",
        "text": "打物体颜色的相近色，使物体变亮。",
        "bbox": [
            92,
            898,
            369,
            913
        ],
        "page_idx": 1
    },
    {
        "type": "text",
        "text": "打物体颜色的互补色，使物体变暗。",
        "bbox": [
            92,
            917,
            369,
            932
        ],
        "page_idx": 1
    },
    {
        "type": "text",
        "text": "采用背景色蓝色打光时：蓝色字体变淡，红色字体加深。",
        "bbox": [
            67,
            55,
            502,
            72
        ],
        "page_idx": 2
    },
    {
        "type": "text",
        "text": "4.扫码枪介绍 ",
        "text_level": 1,
        "bbox": [
            65,
            152,
            230,
            175
        ],
        "page_idx": 3
    },
    {
        "type": "text",
        "text": "常用扫码枪型号：DM262 、DM302",
        "bbox": [
            65,
            218,
            339,
            233
        ],
        "page_idx": 3
    },
    {
        "type": "text",
        "text": "DM262：电源24V，棕正蓝负 ",
        "bbox": [
            65,
            237,
            295,
            250
        ],
        "page_idx": 3
    },
    {
        "type": "text",
        "text": "IP 配置：参考相机 Ip 配置，扫码枪端的 IP 用扫码枪软件修改。",
        "bbox": [
            100,
            255,
            579,
            269
        ],
        "page_idx": 3
    },
    {
        "type": "text",
        "text": "扫码枪指示灯：1.电源灯(绿色)2.训练灯(训练绿色/未训练黄色)3.触发指示灯(读上码闪绿色/未读码闪红色)",
        "bbox": [
            100,
            273,
            917,
            290
        ],
        "page_idx": 3
    },
    {
        "type": "text",
        "text": "4. 网线灯(接通为黄色)5.报警灯(报警时红色灯常亮) ",
        "bbox": [
            240,
            292,
            653,
            307
        ],
        "page_idx": 3
    },
    {
        "type": "text",
        "text": "备份读码参数：软件导出导入cfg格式配置文件，cdc格式文件",
        "bbox": [
            65,
            329,
            549,
            346
        ],
        "page_idx": 3
    },
    {
        "type": "text",
        "text": "5.精度计算 ",
        "text_level": 1,
        "bbox": [
            65,
            387,
            203,
            411
        ],
        "page_idx": 3
    },
    {
        "type": "image",
        "img_path": "images/d480f2fab6093fa1ae5c270b0e6f744aa93ae65e130d5fce61ee72940eb41008.jpg",
        "image_caption": [
            "精度计算"
        ],
        "image_footnote": [],
        "bbox": [
            84,
            521,
            458,
            674
        ],
        "page_idx": 3
    },
    {
        "type": "text",
        "text": "视野为 $\\bar { 5 } . 4 \\mathsf { m m } ^ { * } 4 . 8 \\mathsf { m m }$ 分辨率为 $6 4 0 ^ { * } 4 8 0$ ",
        "bbox": [
            564,
            546,
            865,
            564
        ],
        "page_idx": 3
    },
    {
        "type": "text",
        "text": "精确度视觉工具 $= \\frac { 1 } { 1 0 }$ 像素",
        "bbox": [
            571,
            571,
            803,
            612
        ],
        "page_idx": 3
    },
    {
        "type": "text",
        "text": "视觉精度计算： 单方向视野范围/相机单方向分辨率",
        "bbox": [
            137,
            684,
            756,
            709
        ],
        "page_idx": 3
    },
    {
        "type": "text",
        "text": "相机精度：6.4mm/640像素=0.01mm",
        "bbox": [
            137,
            731,
            566,
            753
        ],
        "page_idx": 3
    },
    {
        "type": "text",
        "text": "测量精度：0.01mm*视觉工具精度=0.01mm*0.1=0.001mm",
        "bbox": [
            139,
            755,
            815,
            776
        ],
        "page_idx": 3
    },
    {
        "type": "text",
        "text": "eg：1.康耐视500w相机拍照，视野为50mm*40mm，所使用的视觉工具精度为¼个像素，求测量精度？（500w相机分辨率为 $2 5 9 2 ^ { * } 1 9 4 4 )$ ）",
        "bbox": [
            63,
            806,
            929,
            840
        ],
        "page_idx": 3
    },
    {
        "type": "text",
        "text": "相机精度:(即像素分辨率) 相机精度=50mm/2592=0.0193mm",
        "bbox": [
            65,
            843,
            534,
            858
        ],
        "page_idx": 3
    },
    {
        "type": "text",
        "text": "测量精度：测量精度 $\\cdot$ 相机精度*视觉工具精度=0.0193mm*¼=0.004825mm",
        "bbox": [
            65,
            862,
            635,
            876
        ],
        "page_idx": 3
    },
    {
        "type": "text",
        "text": "6.码密度计算 ",
        "text_level": 1,
        "bbox": [
            65,
            63,
            230,
            86
        ],
        "page_idx": 4
    },
    {
        "type": "text",
        "text": "含义：码的每个module(模块)的平均像素值 每个模块占了几个像素",
        "bbox": [
            65,
            128,
            603,
            145
        ],
        "page_idx": 4
    },
    {
        "type": "text",
        "text": "意义：它是判断扫码稳定性的一个重要依据，它不是越大越好也不是越小越好，需要控制在一个合理的范围，",
        "bbox": [
            65,
            146,
            917,
            164
        ],
        "page_idx": 4
    },
    {
        "type": "text",
        "text": "二维码一般建议在5~8，一维码建议在3以上",
        "bbox": [
            65,
            165,
            418,
            181
        ],
        "page_idx": 4
    },
    {
        "type": "text",
        "text": "码PMM值计算",
        "text_level": 1,
        "bbox": [
            82,
            186,
            405,
            223
        ],
        "page_idx": 4
    },
    {
        "type": "text",
        "text": "1.视野是 $7 8 m m ^ { \\star } 5 0 m m$ 中间有个二维码尺寸为 $5 m m ^ { \\star } 5 m m$ 二维码是12*12Code ",
        "bbox": [
            82,
            252,
            870,
            272
        ],
        "page_idx": 4
    },
    {
        "type": "text",
        "text": "(通俗来讲就是求此二维码每个模块包含几个像素)",
        "bbox": [
            92,
            277,
            574,
            297
        ],
        "page_idx": 4
    },
    {
        "type": "text",
        "text": "用扫码枪DM50X(752*480)的长边计算",
        "bbox": [
            82,
            300,
            462,
            321
        ],
        "page_idx": 4
    },
    {
        "type": "list",
        "sub_type": "text",
        "list_items": [
            "$\\textcircled{1}$ 先算出视野里每个mm单位所包含的像素个数：",
            "$7 5 2 / 7 8 \\mathsf { m m } = 9 . 6$ 表示每mm有9.6个像素",
            "$\\textcircled{2}$ 再算出每个模块尺寸为多少mm：5/12=0.4166666667mm",
            "$\\textcircled{3}$ 计算码密度：9.6*0.0.4166666667mm $\\cdot$ "
        ],
        "bbox": [
            82,
            325,
            690,
            417
        ],
        "page_idx": 4
    },
    {
        "type": "text",
        "text": "另—种:5mm/78mm*752像素/12=4.017094017094017094017094017094",
        "bbox": [
            82,
            423,
            847,
            442
        ],
        "page_idx": 4
    },
    {
        "type": "text",
        "text": "Fov:60mm*48mm ",
        "bbox": [
            117,
            470,
            196,
            481
        ],
        "page_idx": 4
    },
    {
        "type": "image",
        "img_path": "images/228c2f5901b444ac83e5acd2fd001487bc29e20ac26ad8b4b0b9a93ab74bec2c.jpg",
        "image_caption": [
            "5mm*5mm "
        ],
        "image_footnote": [],
        "bbox": [
            226,
            516,
            290,
            557
        ],
        "page_idx": 4
    },
    {
        "type": "text",
        "text": "code: 12*12 ",
        "bbox": [
            230,
            561,
            282,
            569
        ],
        "page_idx": 4
    },
    {
        "type": "text",
        "text": "1200*960 ",
        "bbox": [
            129,
            615,
            168,
            624
        ],
        "page_idx": 4
    },
    {
        "type": "text",
        "text": "黑色大框是扫码枪或者相机的视野：60mm*48mm，分辨率为1200*960",
        "bbox": [
            84,
            638,
            342,
            646
        ],
        "page_idx": 4
    },
    {
        "type": "text",
        "text": "中间的小框是个二维码尺寸为：5mm*5mm",
        "bbox": [
            85,
            648,
            242,
            656
        ],
        "page_idx": 4
    },
    {
        "type": "text",
        "text": "这个二维码的码值为12*12，也就是说二维码的是有144个模块儿(小格子)组成。",
        "bbox": [
            85,
            657,
            359,
            665
        ],
        "page_idx": 4
    },
    {
        "type": "text",
        "text": "此时计算码密度",
        "bbox": [
            85,
            667,
            144,
            675
        ],
        "page_idx": 4
    },
    {
        "type": "text",
        "text": "1.计算每个像素多长：60mm/1200=0.05mm这是每个小像素点的长宽",
        "bbox": [
            85,
            677,
            337,
            684
        ],
        "page_idx": 4
    },
    {
        "type": "text",
        "text": "2.计算这个二维码长或宽占用了几个像素：5mm/0.05mm=100",
        "bbox": [
            85,
            686,
            307,
            694
        ],
        "page_idx": 4
    },
    {
        "type": "text",
        "text": "3.二维码长边有12个模块儿共计占用100个像素：100/12=8.333",
        "bbox": [
            85,
            695,
            310,
            702
        ],
        "page_idx": 4
    },
    {
        "type": "text",
        "text": "",
        "bbox": [
            85,
            707,
            99,
            713
        ],
        "page_idx": 4
    },
    {
        "type": "text",
        "text": "",
        "bbox": [
            90,
            715,
            245,
            722
        ],
        "page_idx": 4
    },
    {
        "type": "text",
        "text": "二、厂区相关操作",
        "text_level": 1,
        "bbox": [
            67,
            68,
            371,
            99
        ],
        "page_idx": 5
    },
    {
        "type": "list",
        "sub_type": "text",
        "list_items": [
            "1. 了解各 Inspection 的功能、掌握 Vpp 的调试",
            "2. 标定流程、结果及分析"
        ],
        "bbox": [
            65,
            196,
            806,
            336
        ],
        "page_idx": 5
    },
    {
        "type": "list",
        "sub_type": "text",
        "list_items": [
            "$\\cdot$ 确认相机的焦距，视野是否调整 OK，镜头及相机是否松动；",
            "$\\textcircled{2}$ 运动机构是否调整 OK；",
            "$\\cdot$ 软件和视觉软件是否正常，通信是否正常；",
            "$\\textcircled{4}$ 标定所使用的工具是否准备 OK，标定工具是否破损，翘曲；",
            "$\\cdot$ Configuration中棋盘格的尺寸与实际是否匹配；",
            "$\\textcircled{6}$ 机器人吸取或放下棋盘格时，棋盘格是否有滑动现象或者吸不起来；",
            "$\\cdot$ 检查标定误差是否在正常范围；"
        ],
        "bbox": [
            67,
            420,
            559,
            568
        ],
        "page_idx": 5
    },
    {
        "type": "text",
        "text": "3. 标定的异常分析及注意事项",
        "text_level": 1,
        "bbox": [
            67,
            621,
            552,
            651
        ],
        "page_idx": 5
    },
    {
        "type": "text",
        "text": "标定误差大：检查机构走位是否准确，旋转角度是否正确并且准确，标定片尺寸、图片清晰度、标定片标定过程中有没有滑动、标定片模糊、曝光是否合适",
        "bbox": [
            65,
            736,
            927,
            771
        ],
        "page_idx": 5
    },
    {
        "type": "text",
        "text": "标定失败：通讯异常、拍照失败、软件损坏、旋转角度错误、旋转顺序错、",
        "bbox": [
            65,
            774,
            643,
            789
        ],
        "page_idx": 5
    },
    {
        "type": "text",
        "text": "4.视觉异常分析处理",
        "text_level": 1,
        "bbox": [
            65,
            814,
            315,
            837
        ],
        "page_idx": 5
    },
    {
        "type": "text",
        "text": "$\\textcircled{1}$ 相机无法拍照或者连接失败：",
        "bbox": [
            68,
            879,
            319,
            895
        ],
        "page_idx": 5
    },
    {
        "type": "text",
        "text": "确认相机网线是否连接正确 ",
        "bbox": [
            100,
            898,
            319,
            913
        ],
        "page_idx": 5
    },
    {
        "type": "text",
        "text": "如果 VisionPro 可用，打开 Cognex GigE Vision Configuration，查看不拍照的相机是否在左侧的相机列表中。",
        "bbox": [
            100,
            917,
            905,
            933
        ],
        "page_idx": 5
    },
    {
        "type": "text",
        "text": "确认机构是否发送了正确的触发信号。",
        "bbox": [
            100,
            55,
            396,
            72
        ],
        "page_idx": 6
    },
    {
        "type": "text",
        "text": "可能由于主机卡顿，软件卡顿或BUG引起，将计算机关机，约十秒钟后，重新开启计算机",
        "bbox": [
            100,
            74,
            800,
            91
        ],
        "page_idx": 6
    },
    {
        "type": "text",
        "text": "检查相机是否损坏，如坏的话更换相机。",
        "bbox": [
            100,
            92,
            413,
            108
        ],
        "page_idx": 6
    },
    {
        "type": "text",
        "text": "相机配置参数设置不正确，重新查看并配置好正确参数",
        "bbox": [
            100,
            112,
            531,
            127
        ],
        "page_idx": 6
    },
    {
        "type": "text",
        "text": "权限位丢失，检查8704E板卡权限 ",
        "bbox": [
            100,
            130,
            369,
            145
        ],
        "page_idx": 6
    },
    {
        "type": "text",
        "text": "磁盘已满或者图片删除设置参数不合理，重新设置图片保存参数",
        "bbox": [
            100,
            148,
            600,
            164
        ],
        "page_idx": 6
    },
    {
        "type": "text",
        "text": "$\\textcircled{2}$ 相机蓝屏：",
        "text_level": 1,
        "bbox": [
            68,
            167,
            176,
            183
        ],
        "page_idx": 6
    },
    {
        "type": "text",
        "text": "主机 IP 或者相机 IP 有设置错误",
        "bbox": [
            100,
            186,
            344,
            200
        ],
        "page_idx": 6
    },
    {
        "type": "text",
        "text": "巨帧数据包改为 9014、防火墙关闭、ebus 勾选",
        "bbox": [
            100,
            204,
            468,
            219
        ],
        "page_idx": 6
    },
    {
        "type": "text",
        "text": "网口损坏 更换别的网口硬件损坏需更换硬件（网线、相机、图像采集卡）",
        "bbox": [
            100,
            223,
            667,
            239
        ],
        "page_idx": 6
    },
    {
        "type": "text",
        "text": "$\\textcircled{3}$ PMAlign：提高工具运行速度：",
        "text_level": 1,
        "bbox": [
            68,
            241,
            322,
            258
        ],
        "page_idx": 6
    },
    {
        "type": "text",
        "text": "算法由 PatMax 改为 Patquick 会加快运行速度",
        "bbox": [
            67,
            260,
            416,
            275
        ],
        "page_idx": 6
    },
    {
        "type": "text",
        "text": "搜索区域越小搜索速度越快 (宽)x(高)x(角度范围)x(缩放范围)",
        "bbox": [
            67,
            278,
            534,
            294
        ],
        "page_idx": 6
    },
    {
        "type": "text",
        "text": "提高接受阈值搜索变快",
        "bbox": [
            67,
            297,
            248,
            312
        ],
        "page_idx": 6
    },
    {
        "type": "text",
        "text": "减小搜素结果数量执行时间稍变快",
        "bbox": [
            67,
            315,
            336,
            331
        ],
        "page_idx": 6
    },
    {
        "type": "text",
        "text": "精细颗粒度越高，时间越短",
        "bbox": [
            67,
            332,
            282,
            349
        ],
        "page_idx": 6
    },
    {
        "type": "text",
        "text": "粗糙颗粒度越高，时间越短",
        "bbox": [
            67,
            351,
            282,
            368
        ],
        "page_idx": 6
    },
    {
        "type": "text",
        "text": "考虑极性稍稍加快速度",
        "bbox": [
            67,
            370,
            248,
            387
        ],
        "page_idx": 6
    },
    {
        "type": "text",
        "text": "提高对比度以便执行更快",
        "bbox": [
            67,
            390,
            265,
            405
        ],
        "page_idx": 6
    },
    {
        "type": "text",
        "text": "④PMAlign ",
        "text_level": 1,
        "bbox": [
            68,
            407,
            157,
            423
        ],
        "page_idx": 6
    },
    {
        "type": "image",
        "img_path": "images/647ccd1869df29694e65b814403efa9696de2bf705a137475cff8efa077125bd.jpg",
        "image_caption": [
            "PMAlign "
        ],
        "image_footnote": [],
        "bbox": [
            72,
            447,
            438,
            627
        ],
        "page_idx": 6
    },
    {
        "type": "text",
        "text": "图上按钮功能分别表示：",
        "bbox": [
            463,
            450,
            584,
            460
        ],
        "page_idx": 6
    },
    {
        "type": "list",
        "sub_type": "text",
        "list_items": [
            "1.运行",
            "2.电子模式",
            "3.本地显示",
            "4.浮动显示 ",
            "5.打开 ",
            "6.保存 ",
            "7.另存 ",
            "8.复位",
            "9.图像掩膜编辑器",
            "10.建模器",
            "11.帮助 "
        ],
        "bbox": [
            465,
            461,
            554,
            565
        ],
        "page_idx": 6
    },
    {
        "type": "text",
        "text": "⑤Histogram",
        "text_level": 1,
        "bbox": [
            68,
            630,
            169,
            646
        ],
        "page_idx": 6
    },
    {
        "type": "image",
        "img_path": "images/4bffb10311fb2277e2463355d42d7ce7608dea2117ffb6e390b57d77ea832b92.jpg",
        "image_caption": [
            ""
        ],
        "image_footnote": [],
        "bbox": [
            85,
            680,
            324,
            780
        ],
        "page_idx": 6
    },
    {
        "type": "list",
        "sub_type": "text",
        "list_items": [
            "Minimum：最小值灰度最大值 值灰度最大值",
            "Maximum：最大值灰度最小值 值灰度最小值",
            "Median:中值值比例刚过50% ",
            "Mode:模式 灰度值占比最",
            "Mean：平均值灰度平均值 灰度平均值",
            "Std.Dey.:标准差，灰度标准差 灰度标准差",
            "Variance:方差 灰度方差 灰度方差 ",
            "Samples:示例 区域内总像素数 区域内总像素数"
        ],
        "bbox": [
            346,
            686,
            492,
            752
        ],
        "page_idx": 6
    },
    {
        "type": "list",
        "sub_type": "text",
        "list_items": [
            "比例刚过50%对应的灰度值 ",
            "灰度值占比最高的像毒的灰度值"
        ],
        "bbox": [
            421,
            686,
            564,
            752
        ],
        "page_idx": 6
    },
    {
        "type": "text",
        "text": "三、VisionPro Tools 应用",
        "text_level": 1,
        "bbox": [
            67,
            68,
            460,
            98
        ],
        "page_idx": 7
    },
    {
        "type": "text",
        "text": "1. Image Source：",
        "text_level": 1,
        "bbox": [
            67,
            193,
            285,
            215
        ],
        "page_idx": 7
    },
    {
        "type": "text",
        "text": "采图方式：加载文件、加载文件夹、相机取像",
        "bbox": [
            100,
            256,
            460,
            272
        ],
        "page_idx": 7
    },
    {
        "type": "text",
        "text": "支持的图像格式：.idb 、.cdb、.bmp、.tif、.jpg、.png",
        "bbox": [
            100,
            275,
            512,
            292
        ],
        "page_idx": 7
    },
    {
        "type": "text",
        "text": "2.CogAcqFifo：配置相机取像",
        "text_level": 1,
        "bbox": [
            65,
            302,
            379,
            323
        ],
        "page_idx": 7
    },
    {
        "type": "text",
        "text": "$\\textcircled{1}$ 选择相机型号 $\\cdot$ 选择相机格式(Mono、Mono12、Mono12Packed、YUV422Packed) $\\textcircled{3}$ 修改曝光、对比度、亮度、超时期(这几项一般都为默认) $\\textcircled{4}$ 触发方式：Manual(手动触发) 、Free Run(自由触发)、Hardware Auto(硬件触发-飞拍项目)、Hardware Semi-Auto(硬件半自动触发)",
        "bbox": [
            65,
            330,
            927,
            382
        ],
        "page_idx": 7
    },
    {
        "type": "text",
        "text": "Hardware Auto：根据电压变化，需设置极性，由低到高或者由高到低去触发，此极性需和光源触发极性一致。",
        "bbox": [
            65,
            386,
            927,
            420
        ],
        "page_idx": 7
    },
    {
        "type": "text",
        "text": "Hardware Semi-Auto：需要机构和视觉各自发送一个触发信号，先硬触发信号，再相机触发信号， ",
        "bbox": [
            100,
            423,
            845,
            439
        ],
        "page_idx": 7
    },
    {
        "type": "text",
        "text": "3.CogImageFileTool：从 idb 格式文件中读取图片(读取模式) 或者 添加图片(写入模式)",
        "text_level": 1,
        "bbox": [
            65,
            450,
            825,
            469
        ],
        "page_idx": 7
    },
    {
        "type": "text",
        "text": "操作步骤：",
        "text_level": 1,
        "bbox": [
            100,
            479,
            184,
            494
        ],
        "page_idx": 7
    },
    {
        "type": "text",
        "text": "读取模式：不需要输入图像，在工具中选择\"打开ImageFile\"按钮选择idb格式图片文件点击运行预览，并可以当做图像源给别的工具提供图像。",
        "bbox": [
            65,
            497,
            927,
            531
        ],
        "page_idx": 7
    },
    {
        "type": "text",
        "text": "写入模式：",
        "text_level": 1,
        "bbox": [
            109,
            535,
            191,
            550
        ],
        "page_idx": 7
    },
    {
        "type": "list",
        "sub_type": "text",
        "list_items": [
            "$\\textcircled{1}$ 连接图像后 在工具中选择\"打开ImageFile\"按钮，点开录制模式后点击工具外层的运行，会将外部连接的图像录制进打开的idb格式的文件中",
            "$\\textcircled{2}$ 连接图像后 在工具中选择\"创建新的ImageFile\"按钮 在需要的路径里创建一个新的idb格式文件，点击工具外层的运行，开始在新创建的idb格式文件中添加图片"
        ],
        "bbox": [
            117,
            552,
            899,
            624
        ],
        "page_idx": 7
    },
    {
        "type": "text",
        "text": "4.1.CogCalibCheckerboardTool：通过创建一个标定对象来关联图像中的空间和物理空间",
        "text_level": 1,
        "bbox": [
            65,
            636,
            919,
            656
        ],
        "page_idx": 7
    },
    {
        "type": "text",
        "text": "作用：校正图形畸变 建立实际坐标与图像坐标的对应关系 直白点： 建立图像和机构的关联关系用棋盘格标定：",
        "bbox": [
            82,
            664,
            853,
            697
        ],
        "page_idx": 7
    },
    {
        "type": "text",
        "text": "棋盘格标定是使用一个棋盘格来计算像素和真实单位之间的转换",
        "bbox": [
            107,
            701,
            608,
            715
        ],
        "page_idx": 7
    },
    {
        "type": "text",
        "text": "可以计算线性或者非线性转换： 非线性转换用于说明光学 和/或 透视扭曲的情况",
        "bbox": [
            107,
            719,
            732,
            734
        ],
        "page_idx": 7
    },
    {
        "type": "text",
        "text": "图像扭曲的产生及分类：",
        "bbox": [
            100,
            738,
            290,
            753
        ],
        "page_idx": 7
    },
    {
        "type": "text",
        "text": "产生：是由于透镜制造精度以及组装工艺的偏差从而导致原始图像失真的现象",
        "bbox": [
            107,
            756,
            712,
            772
        ],
        "page_idx": 7
    },
    {
        "type": "text",
        "text": "分类：线性扭曲：纵向失真(横向压缩) 横向失真(纵向压缩)",
        "bbox": [
            107,
            775,
            563,
            791
        ],
        "page_idx": 7
    },
    {
        "type": "text",
        "text": "非线性扭曲：桶形畸变 枕形畸变",
        "bbox": [
            171,
            794,
            426,
            809
        ],
        "page_idx": 7
    },
    {
        "type": "text",
        "text": "标定流程图：采集表定图像 棋盘格物理尺寸 标定工具计算标定结果 (仅限非线性模式)",
        "bbox": [
            100,
            812,
            763,
            828
        ],
        "page_idx": 7
    },
    {
        "type": "text",
        "text": "棋盘格标定原点获取：校准板有一个原点(比如两个交叉矩形的右下交点)",
        "bbox": [
            100,
            831,
            663,
            846
        ],
        "page_idx": 7
    },
    {
        "type": "text",
        "text": "若没有：没有二维码的 原点则是图像左上角",
        "bbox": [
            240,
            848,
            586,
            865
        ],
        "page_idx": 7
    },
    {
        "type": "text",
        "text": "有二维码的原点则是二维码",
        "bbox": [
            314,
            868,
            529,
            883
        ],
        "page_idx": 7
    },
    {
        "type": "text",
        "text": "操作流程：",
        "text_level": 1,
        "bbox": [
            100,
            885,
            184,
            901
        ],
        "page_idx": 7
    },
    {
        "type": "list",
        "sub_type": "text",
        "list_items": [
            "$\\textcircled{1}$ 获取标定片图像：保证曝光合适 焦距清楚 标定片尽量布满视野 标定片不要翘曲",
            "$\\textcircled{2}$ 添加标定工具：CogCalibCheckerBoardTool 工具 连接图像"
        ],
        "bbox": [
            109,
            904,
            752,
            939
        ],
        "page_idx": 7
    },
    {
        "type": "list",
        "sub_type": "text",
        "list_items": [
            "$\\textcircled{3}$ 设置线性或非线性模式 输入标定片 XY 尺寸 $( 0 . 2 5 0 . 5 1 2 \\mathrm { { m m } ) }$ 点抓取校正图像 按钮",
            "$\\textcircled{4}$ 修改校正原点(可选项)：可以选择修改校准空间的原点，设置原点空间，X轴旋转，X轴旋转空间，交换左右手使用习惯",
            "$\\textcircled{5}$ 计算标定结果： 点击计算校正按钮，查看非扭曲的校正图像",
            "$\\textcircled{6}$ 查看标定结果：查看磁块各个角的结果 未校正的XY和原始的已校正的XY坐标的差异"
        ],
        "bbox": [
            65,
            55,
            929,
            145
        ],
        "page_idx": 8
    },
    {
        "type": "text",
        "text": "查看计算的非线性方程的系数：",
        "bbox": [
            136,
            149,
            379,
            162
        ],
        "page_idx": 8
    },
    {
        "type": "text",
        "text": "纵横比：校正前后XY方向的纵横比 越接近1越好",
        "bbox": [
            134,
            167,
            522,
            181
        ],
        "page_idx": 8
    },
    {
        "type": "text",
        "text": "RMS误差：越接近0越好 这个是像素坐标和标定片坐标差值的方",
        "bbox": [
            134,
            186,
            645,
            200
        ],
        "page_idx": 8
    },
    {
        "type": "text",
        "text": "CheckerBoard 标定的工作原理：采集图像中的顶点-黑白相间的交点",
        "bbox": [
            100,
            205,
            621,
            219
        ],
        "page_idx": 8
    },
    {
        "type": "text",
        "text": "原始校正空间中的顶点，基于所提供的的磁块尺寸信息 比较两组点",
        "bbox": [
            248,
            223,
            774,
            237
        ],
        "page_idx": 8
    },
    {
        "type": "text",
        "text": "将标定结果输出：表示两个图像中一旦计算出转换，只要将校准的输出图像传递给检验工具的输入图像",
        "bbox": [
            100,
            241,
            900,
            256
        ],
        "page_idx": 8
    },
    {
        "type": "text",
        "text": "校正的图像将被传递给该工具",
        "bbox": [
            524,
            260,
            759,
            275
        ],
        "page_idx": 8
    },
    {
        "type": "text",
        "text": "4.2.CogCalibNPointToNPointTool：不能校正非线性畸变",
        "text_level": 1,
        "bbox": [
            65,
            287,
            678,
            307
        ],
        "page_idx": 8
    },
    {
        "type": "text",
        "text": "操作步骤：连接图像 输入三组像素坐标和三组物理坐标 抓取计算校正",
        "bbox": [
            100,
            315,
            647,
            331
        ],
        "page_idx": 8
    },
    {
        "type": "text",
        "text": "结果：XY 平移 缩放 纵横比 旋转 倾斜 RMS 误差(等同 checkboard)",
        "bbox": [
            100,
            334,
            600,
            349
        ],
        "page_idx": 8
    },
    {
        "type": "text",
        "text": "5.CogCreation：包含创造圆、创造椭圆、创造文本、创造点平分线、创造平行线、创造垂线、创造线、创造线段平分线、创造线段",
        "bbox": [
            65,
            381,
            927,
            424
        ],
        "page_idx": 8
    },
    {
        "type": "text",
        "text": "PS：工具名按照 visionPro 工具集工具顺序排列",
        "bbox": [
            134,
            426,
            497,
            442
        ],
        "page_idx": 8
    },
    {
        "type": "text",
        "text": "操作步骤：连接图像，连接工具需要的XY坐标(起点 终点 圆心)、线段、线、半径、角度等信息给工具后点击运行查看结果",
        "bbox": [
            65,
            445,
            927,
            479
        ],
        "page_idx": 8
    },
    {
        "type": "text",
        "text": "6.CogPMAlignTool：图案位置搜索工具 可在图像中找到你训练的特征所在的位置",
        "text_level": 1,
        "bbox": [
            65,
            508,
            800,
            531
        ],
        "page_idx": 8
    },
    {
        "type": "text",
        "text": "等信息",
        "bbox": [
            65,
            538,
            124,
            552
        ],
        "page_idx": 8
    },
    {
        "type": "text",
        "text": "基于边缘特征的模板而不是基于像素的模板匹配，比像素格栅表现更快捷准确支持旋转和缩放",
        "bbox": [
            240,
            556,
            847,
            590
        ],
        "page_idx": 8
    },
    {
        "type": "text",
        "text": "三种主要算法：PatMax（精度最高）, PatQuick（速度最快）, PatFlex（细节最佳）",
        "bbox": [
            65,
            593,
            687,
            609
        ],
        "page_idx": 8
    },
    {
        "type": "text",
        "text": "建立模版的三大要素：位置、尺寸、角度",
        "bbox": [
            65,
            612,
            389,
            627
        ],
        "page_idx": 8
    },
    {
        "type": "text",
        "text": "在匹配特征过程中:黄色表示粗糙特征，绿色表示精细特征",
        "bbox": [
            65,
            630,
            517,
            646
        ],
        "page_idx": 8
    },
    {
        "type": "text",
        "text": "在使用模板工具进行模板建立的时候要注意遵循的三项原则 ：特征唯一、对比度明显、形状轮廓明显。",
        "bbox": [
            65,
            648,
            858,
            665
        ],
        "page_idx": 8
    },
    {
        "type": "text",
        "text": "操作步骤：",
        "text_level": 1,
        "bbox": [
            100,
            686,
            184,
            701
        ],
        "page_idx": 8
    },
    {
        "type": "list",
        "sub_type": "text",
        "list_items": [
            "$\\cdot$ 输入图像 $\\textcircled{2}$ 点击抓取图像，选择训练模式(建模掩膜)，选择合适的算法(patmax patquick)",
            "$\\textcircled{3}$ 切换到当前训练图像，调整训练区域位置及形状，调整训练中心原点"
        ],
        "bbox": [
            109,
            705,
            810,
            739
        ],
        "page_idx": 8
    },
    {
        "type": "list",
        "sub_type": "text",
        "list_items": [
            "$\\textcircled{4}$ 在运行参数选择合适的查找概数(结果数)、接受阈值(允许结果的最低相似度)、是否考虑杂斑、角度及尺寸的缩放",
            "$\\cdot$ 点击训练，运行查看结果"
        ],
        "bbox": [
            65,
            741,
            927,
            794
        ],
        "page_idx": 8
    },
    {
        "type": "text",
        "text": "掩膜：分为将不需要的特征掩盖掉，或者将整幅图像掩掉，将需要的特征露出来。",
        "bbox": [
            65,
            797,
            695,
            812
        ],
        "page_idx": 8
    },
    {
        "type": "text",
        "text": "建模：可以自动提取需要的特征或者手动添加具体的特征，需要设置极性 。",
        "bbox": [
            65,
            816,
            648,
            831
        ],
        "page_idx": 8
    },
    {
        "type": "text",
        "text": "7.1.Caliper()：能够辨别图像中的边线和边线对子 报告边线对子中的边线位置和边线之间的距离",
        "text_level": 1,
        "bbox": [
            65,
            862,
            873,
            883
        ],
        "page_idx": 8
    },
    {
        "type": "text",
        "text": "工作极性方法是： 由暗到明 ，由明到暗 ，任意极性 。",
        "bbox": [
            65,
            889,
            482,
            904
        ],
        "page_idx": 8
    },
    {
        "type": "text",
        "text": "两个工作模式：单个边缘、边缘对",
        "bbox": [
            65,
            908,
            336,
            923
        ],
        "page_idx": 8
    },
    {
        "type": "text",
        "text": "Caliper 工具中： 代表卡尺的 搜索 方向 代表卡尺的 _投影 方向，在抓边过",
        "bbox": [
            65,
            927,
            678,
            942
        ],
        "page_idx": 8
    },
    {
        "type": "text",
        "text": "程中， 投影 方向要与查找的边缘平行。",
        "bbox": [
            65,
            55,
            371,
            72
        ],
        "page_idx": 9
    },
    {
        "type": "text",
        "text": "操作步骤： $\\cdot$ 连接图像 $\\textcircled{2}$ 定义目标区域(扫描方向与查找方向垂直，投影方向与查找方向平行)$\\cdot$ 设置基本参数 选择建立计分标准 测试评价结果其中实心箭头是搜索方向 空心箭头是投影方向",
        "bbox": [
            100,
            92,
            830,
            146
        ],
        "page_idx": 9
    },
    {
        "type": "text",
        "text": "参数设置：边缘模式 极性 对比度阈值 过滤一半像素(设置为过渡像素个数的一半) 最大结果数 边缘对宽度(边缘对模式才有 会影响得分)",
        "bbox": [
            65,
            148,
            929,
            183
        ],
        "page_idx": 9
    },
    {
        "type": "text",
        "text": "输出结果：分数 edge0(结果数的索引) 位置(抓的结果离卡尺中心的距离) xY 计分函数 对比度应用：工具测量元件宽度 测量元件之间的距离",
        "bbox": [
            99,
            186,
            811,
            221
        ],
        "page_idx": 9
    },
    {
        "type": "text",
        "text": "7.2.Find/Fitline：需掌握包含抓圆、抓拐角点、抓椭圆、抓边、拟合圆、拟合椭圆、拟合线工具。",
        "bbox": [
            65,
            250,
            895,
            271
        ],
        "page_idx": 9
    },
    {
        "type": "list",
        "sub_type": "text",
        "list_items": [
            "$\\textcircled{1}$ 拟合工具操作步骤：连接图像后输入需要的若干组坐标(两点拟合线、三点拟合圆、五点拟合椭圆)",
            "$\\textcircled{2}$ CogFindLineTool："
        ],
        "bbox": [
            65,
            285,
            929,
            363
        ],
        "page_idx": 9
    },
    {
        "type": "text",
        "text": "使用和常见参数介绍：",
        "text_level": 1,
        "bbox": [
            109,
            370,
            282,
            387
        ],
        "page_idx": 9
    },
    {
        "type": "text",
        "text": "是在图像指定区域运行一系列 Caliper 工具以定位多个边缘点，然后运行",
        "bbox": [
            115,
            388,
            685,
            406
        ],
        "page_idx": 9
    },
    {
        "type": "text",
        "text": "底层的 FitLine 工具将他们拟合成直线。相当于 Caliper 工具+FitLine 工具",
        "bbox": [
            134,
            407,
            685,
            424
        ],
        "page_idx": 9
    },
    {
        "type": "text",
        "text": "要求输入图像",
        "bbox": [
            109,
            426,
            221,
            442
        ],
        "page_idx": 9
    },
    {
        "type": "text",
        "text": "基本参数：",
        "text_level": 1,
        "bbox": [
            109,
            445,
            193,
            460
        ],
        "page_idx": 9
    },
    {
        "type": "text",
        "text": "卡尺数量：需要找的点的数量",
        "bbox": [
            117,
            463,
            352,
            479
        ],
        "page_idx": 9
    },
    {
        "type": "text",
        "text": "搜索长度：每个搜索卡尺的长度",
        "bbox": [
            137,
            482,
            389,
            498
        ],
        "page_idx": 9
    },
    {
        "type": "text",
        "text": "投影长度：每个搜索卡尺的宽度",
        "bbox": [
            137,
            500,
            389,
            516
        ],
        "page_idx": 9
    },
    {
        "type": "text",
        "text": "搜索方向：每个搜索卡尺从一端到另一端的方向",
        "bbox": [
            137,
            519,
            512,
            535
        ],
        "page_idx": 9
    },
    {
        "type": "text",
        "text": "忽略点数：忽略找到的卡尺数量",
        "bbox": [
            137,
            538,
            389,
            552
        ],
        "page_idx": 9
    },
    {
        "type": "text",
        "text": "极性设置: 由明到暗由暗到明 任何极性",
        "bbox": [
            137,
            556,
            440,
            571
        ],
        "page_idx": 9
    },
    {
        "type": "text",
        "text": "对比度阈值：边缘点所需的最小对比度",
        "bbox": [
            137,
            574,
            440,
            590
        ],
        "page_idx": 9
    },
    {
        "type": "text",
        "text": "过滤一半像素：指定过滤器的半宽 ",
        "bbox": [
            137,
            593,
            406,
            609
        ],
        "page_idx": 9
    },
    {
        "type": "text",
        "text": "③CogFindCircleTool：",
        "bbox": [
            105,
            619,
            351,
            640
        ],
        "page_idx": 9
    },
    {
        "type": "text",
        "text": "使用和常见参数介绍：比起findline 多出半径限制和角度范围",
        "bbox": [
            107,
            649,
            586,
            665
        ],
        "page_idx": 9
    },
    {
        "type": "text",
        "text": "半径限制：限制搜索圆的半径",
        "bbox": [
            137,
            667,
            371,
            683
        ],
        "page_idx": 9
    },
    {
        "type": "text",
        "text": "角度范围：决定圆的角度",
        "bbox": [
            137,
            686,
            336,
            702
        ],
        "page_idx": 9
    },
    {
        "type": "text",
        "text": "8.CreationTool：创造工具，创造线段、线、平行线、垂线、圆等。",
        "bbox": [
            65,
            732,
            667,
            751
        ],
        "page_idx": 9
    },
    {
        "type": "text",
        "text": "连接图像、连接需要的点、线、角度、长度等。或者打开工具自定义点位置，角度，角度大小等。",
        "bbox": [
            65,
            760,
            818,
            777
        ],
        "page_idx": 9
    },
    {
        "type": "text",
        "text": "9. Measurement：测量工具包含求角度和距离",
        "bbox": [
            65,
            788,
            519,
            806
        ],
        "page_idx": 9
    },
    {
        "type": "text",
        "text": "角度：线线角度、点点角度、",
        "bbox": [
            105,
            816,
            329,
            832
        ],
        "page_idx": 9
    },
    {
        "type": "text",
        "text": "操作步骤： $\\textcircled{1}$ 连接图像 $\\textcircled{2}$ 输入工具需要的点和角度参数 $\\textcircled{3}$ 点击运行查看结果",
        "bbox": [
            104,
            834,
            697,
            850
        ],
        "page_idx": 9
    },
    {
        "type": "text",
        "text": "求距离(最短距离)：圆到圆的距离、线到圆的距离、线到椭圆的距离、点到圆的距离、点到椭圆的距离、点到线的距离、点到点的距离、点到线段的距离、线段到圆的距离、线段到椭圆的距离、线段到线的距离、线段到线段之间的距离",
        "bbox": [
            65,
            852,
            929,
            906
        ],
        "page_idx": 9
    },
    {
        "type": "text",
        "text": "操作步骤： $\\cdot$ 连接图像 $\\cdot$ 输入工具需要的点、线段、线、圆、椭圆等参数 $\\cdot$ 点击运行查看结果",
        "bbox": [
            100,
            908,
            835,
            925
        ],
        "page_idx": 9
    },
    {
        "type": "text",
        "text": "10.CogResultsAnalysisTool&DataAnalysis：",
        "text_level": 1,
        "bbox": [
            65,
            64,
            621,
            86
        ],
        "page_idx": 10
    },
    {
        "type": "text",
        "text": "结果分析工具可提供一组表达式，",
        "bbox": [
            667,
            68,
            934,
            84
        ],
        "page_idx": 10
    },
    {
        "type": "text",
        "text": "将让工具组在最近运行时间以提供通过警告级别 拒绝级别的结果 表达式中包含各种运算符(加减乘除等)",
        "bbox": [
            65,
            92,
            875,
            109
        ],
        "page_idx": 10
    },
    {
        "type": "text",
        "text": "操作步骤：添加工具后打开工具点击\"添加新值输入\"后可在外部连接值进来",
        "bbox": [
            100,
            112,
            690,
            127
        ],
        "page_idx": 10
    },
    {
        "type": "text",
        "text": "点击 \"添加表达式\"可对已经输入进来的值进行运算 并对结果进行判断 ",
        "bbox": [
            181,
            130,
            719,
            145
        ],
        "page_idx": 10
    },
    {
        "type": "text",
        "text": "DataAnalysis：输入需要判定的值，根据需求勾选拒绝、警告的上限、下限。勾选后设定阈值。不符合要求时会提示得到拒绝的结果",
        "bbox": [
            65,
            167,
            927,
            202
        ],
        "page_idx": 10
    },
    {
        "type": "text",
        "text": "11.CogHistogramTool：灰度直方图工具：用于计算图像中像素的基本统计度量，例如平均灰度值 灰度值中值，标准差 方差等",
        "bbox": [
            65,
            212,
            927,
            256
        ],
        "page_idx": 10
    },
    {
        "type": "text",
        "text": "操作步骤：输入图像 框选需要检测灰度的区域 点击运行查看结果",
        "bbox": [
            100,
            260,
            608,
            275
        ],
        "page_idx": 10
    },
    {
        "type": "text",
        "text": "minimum：最小值 Maximum：最大值Mode：数量最多对应的灰阶值",
        "bbox": [
            100,
            279,
            633,
            294
        ],
        "page_idx": 10
    },
    {
        "type": "text",
        "text": "Mean：灰度均值，即算数平均值 Std.Dev：平均方差 Variance：方差",
        "bbox": [
            100,
            297,
            626,
            312
        ],
        "page_idx": 10
    },
    {
        "type": "text",
        "text": "Samples：图像中 0-255 灰阶像素数量总和",
        "bbox": [
            100,
            316,
            428,
            331
        ],
        "page_idx": 10
    },
    {
        "type": "text",
        "text": "Median：灰度值中值，即累计%首次超过 $\\cdot$ 对应的灰阶值",
        "bbox": [
            100,
            334,
            561,
            349
        ],
        "page_idx": 10
    },
    {
        "type": "text",
        "text": "Data：如 8 位图像，0-255 灰阶数据统计表格，GeryLevel 灰阶 Count 对应灰阶像素个数 Cumulative%累计%",
        "bbox": [
            100,
            353,
            912,
            369
        ],
        "page_idx": 10
    },
    {
        "type": "text",
        "text": "12.CogBlobTool：求面积 求个数 求质心坐标 XY",
        "bbox": [
            65,
            380,
            527,
            400
        ],
        "page_idx": 10
    },
    {
        "type": "text",
        "text": "应用场景：对象在尺寸形状方向上有很大差异 在背景中没有明显灰度阴影的对象 对象没有重叠或者连接",
        "bbox": [
            100,
            407,
            909,
            423
        ],
        "page_idx": 10
    },
    {
        "type": "text",
        "text": "不推荐应用场景：低对比度 在两种灰阶范围内不能突出主要特征需要匹配模板",
        "bbox": [
            100,
            426,
            714,
            442
        ],
        "page_idx": 10
    },
    {
        "type": "text",
        "text": "操作步骤： $\\cdot$ 连接输入图像 $\\cdot$ 选择极性若需要可以选择模式(硬阈值软阈值等并设置相关阈值等参数)",
        "bbox": [
            100,
            445,
            880,
            461
        ],
        "page_idx": 10
    },
    {
        "type": "text",
        "text": "$\\cdot$ 调整需要检测的区域 $\\textcircled{4}$ 运行查看结果 $\\cdot$ 根据实际情况在“测得尺寸”界面筛选出需要保留的",
        "bbox": [
            181,
            464,
            924,
            480
        ],
        "page_idx": 10
    },
    {
        "type": "text",
        "text": "斑点",
        "bbox": [
            65,
            483,
            107,
            497
        ],
        "page_idx": 10
    },
    {
        "type": "text",
        "text": "一、上机操作题。 （100 分）",
        "text_level": 1,
        "bbox": [
            65,
            512,
            568,
            544
        ],
        "page_idx": 10
    },
    {
        "type": "text",
        "text": "1、如下图，用文件夹中图片dot.idb操作如下试题。",
        "bbox": [
            65,
            580,
            529,
            598
        ],
        "page_idx": 10
    },
    {
        "type": "list",
        "sub_type": "text",
        "list_items": [
            "$\\textcircled{1}$ 求如下图片中黑色斑点的个数并添加到输出端。（25 分）",
            "$\\textcircled{2}$ 求圆 1 和圆 6 两个斑点的中心距离并添加到输出端。(25 分）"
        ],
        "bbox": [
            65,
            630,
            613,
            697
        ],
        "page_idx": 10
    },
    {
        "type": "text",
        "text": "做题步骤： $\\cdot$ 多张图像，需要跟随，用左侧三个圆，加上右侧中间圆做模板(这四个圆是每幅图像",
        "bbox": [
            65,
            728,
            924,
            746
        ],
        "page_idx": 10
    },
    {
        "type": "text",
        "text": "共有的特征，可以用掩膜掩去右上角和右下角的圆)。",
        "bbox": [
            65,
            772,
            529,
            789
        ],
        "page_idx": 10
    },
    {
        "type": "list",
        "sub_type": "text",
        "list_items": [
            "$\\cdot$ 做第一问，斑点工具选择正确极性黑底白点。将count终端输出",
            "$\\cdot$ 两个抓圆工具得来圆1 6的中心，然后用点点测距工具测量圆心1到圆心6的距离并把"
        ],
        "bbox": [
            65,
            821,
            855,
            888
        ],
        "page_idx": 10
    },
    {
        "type": "text",
        "text": "Distance 终端输出。",
        "bbox": [
            65,
            914,
            245,
            931
        ],
        "page_idx": 10
    },
    {
        "type": "image",
        "img_path": "images/867154575c0ed330771212744af207b75bf97c844a8459eaf2d06cf4068e8a02.jpg",
        "image_caption": [],
        "image_footnote": [],
        "bbox": [
            68,
            52,
            302,
            258
        ],
        "page_idx": 11
    },
    {
        "type": "text",
        "text": "2、如下图，用文件夹中图片 bracket_mask.bmp 操作如下试题",
        "text_level": 1,
        "bbox": [
            65,
            266,
            789,
            290
        ],
        "page_idx": 11
    },
    {
        "type": "list",
        "sub_type": "text",
        "list_items": [
            "$\\textcircled{1}$ 求出如下图 P1 和 P2 点的连线，并求出 P1 和 P2 连线中点的坐标，并添加到输出端。 （20",
            "分）ps：线段才有中点)",
            "$\\textcircled{2}$ 求下图区域 1 和区域 2 的中心点，通过两个中心点创造一条线段。（30）"
        ],
        "bbox": [
            65,
            318,
            895,
            429
        ],
        "page_idx": 11
    },
    {
        "type": "image",
        "img_path": "images/e85132fcaa57f10b9a50afb762e535f20271241888cd860fd5898f97e9a34f2d.jpg",
        "image_caption": [],
        "image_footnote": [],
        "bbox": [
            68,
            448,
            527,
            690
        ],
        "page_idx": 11
    },
    {
        "type": "text",
        "text": "做题步骤：这张图是bmp单张图像，所以可以不用模板 $^ +$ 定位工具",
        "bbox": [
            65,
            692,
            658,
            709
        ],
        "page_idx": 11
    },
    {
        "type": "list",
        "sub_type": "text",
        "list_items": [
            "$\\cdot$ 和 P2 点可以用三个 findline 抓出三条直线，然后用 intersection 交点工具求出两个交点。",
            "$\\cdot$ 求区域1和区域2的中心（求矩形四条边（findline），四个交点intersection工具，两个对角线 fitline，求中心 intersection 工具）"
        ],
        "bbox": [
            65,
            713,
            927,
            771
        ],
        "page_idx": 11
    },
    {
        "type": "text",
        "text": "将两个中心点链接给创造线段工具 CogCreateSegmentTool1 。",
        "bbox": [
            65,
            775,
            626,
            793
        ],
        "page_idx": 11
    },
    {
        "type": "text",
        "text": "3、使用 Blob.idb 文件，做出如下实操试题，并保存为 Job 格式。",
        "text_level": 1,
        "bbox": [
            65,
            875,
            786,
            897
        ],
        "page_idx": 11
    },
    {
        "type": "text",
        "text": "$\\textcircled{1}$ 求如图 Blob 的面积，并用终端输出。（15 分）",
        "bbox": [
            104,
            904,
            561,
            923
        ],
        "page_idx": 11
    },
    {
        "type": "text",
        "text": "$\\textcircled{2}$ 求 P 点的坐标，并用终端输出。（15 分）",
        "bbox": [
            105,
            55,
            512,
            74
        ],
        "page_idx": 12
    },
    {
        "type": "image",
        "img_path": "images/b170557251bc310311895d130dc4aedef9cd9f6773bf22d390ab706fed86e7a8.jpg",
        "image_caption": [],
        "image_footnote": [],
        "bbox": [
            181,
            140,
            394,
            233
        ],
        "page_idx": 12
    },
    {
        "type": "text",
        "text": "做题步骤： $\\cdot$ 加载图片，多张图 用模板工具黑色方块做模板（两张图共有并且一样的特征是方块。）和定位工具。",
        "bbox": [
            63,
            337,
            927,
            394
        ],
        "page_idx": 12
    },
    {
        "type": "list",
        "sub_type": "text",
        "list_items": [
            "$\\cdot$ 斑点工具，选择极性，筛选面积得到黑色斑点。 用整幅图像筛选就行。",
            "$\\textcircled{3}$ 求中心。参考题目 2 的做题步骤 2。"
        ],
        "bbox": [
            65,
            412,
            712,
            467
        ],
        "page_idx": 12
    },
    {
        "type": "text",
        "text": "4.、Vision Tools 上机操作题。 （30 分）",
        "text_level": 1,
        "bbox": [
            65,
            556,
            786,
            589
        ],
        "page_idx": 12
    },
    {
        "type": "text",
        "text": "1,使用加载的图片文件，完成如下操作题。(作业完成后保存为 Job 格式,命名方式为自己的姓名.)",
        "bbox": [
            35,
            593,
            917,
            612
        ],
        "page_idx": 12
    },
    {
        "type": "list",
        "sub_type": "text",
        "list_items": [
            "$\\textcircled{1}$ 求出两个零件主体中心点 P 和 Q 点的坐标，并使用终端进行输出。（15 分）",
            "$\\textcircled{2}$ 求 Q 点到 Z 点的距离，并使用终端进行输出。（15 分）"
        ],
        "bbox": [
            36,
            615,
            741,
            652
        ],
        "page_idx": 12
    },
    {
        "type": "image",
        "img_path": "images/7b2f4bb5e40ef0b0afdea87cfde47074ac81c370a6be26b399bd502200764600.jpg",
        "image_caption": [],
        "image_footnote": [],
        "bbox": [
            70,
            653,
            450,
            857
        ],
        "page_idx": 12
    },
    {
        "type": "text",
        "text": "做题步骤： $\\cdot$ 分别求出PQ的中心坐标，两个求中心的步骤得来两个中心就行。记得终端输出 P",
        "bbox": [
            65,
            902,
            932,
            922
        ],
        "page_idx": 12
    },
    {
        "type": "text",
        "text": "和Q点的XY坐标。",
        "bbox": [
            65,
            65,
            235,
            82
        ],
        "page_idx": 13
    },
    {
        "type": "text",
        "text": "②Q中心有了，用intersection工具求出右下图案的右上角的交点Z，",
        "bbox": [
            65,
            102,
            675,
            118
        ],
        "page_idx": 13
    },
    {
        "type": "text",
        "text": "用点点测距工具测得点Q到Z的距离。输出终端",
        "bbox": [
            65,
            139,
            499,
            156
        ],
        "page_idx": 13
    },
    {
        "type": "text",
        "text": "5.机试试题（100 分）：",
        "text_level": 1,
        "bbox": [
            65,
            193,
            321,
            212
        ],
        "page_idx": 13
    },
    {
        "type": "text",
        "text": "（作业保存为 Quickbuild 格式，命名方式为：姓名 $+$ 身份证号。每人作业只收集一份 Quickbuild。）",
        "bbox": [
            75,
            223,
            815,
            239
        ],
        "page_idx": 13
    },
    {
        "type": "text",
        "text": "1. 查找 image1 中",
        "text_level": 1,
        "bbox": [
            67,
            250,
            231,
            268
        ],
        "page_idx": 13
    },
    {
        "type": "list",
        "sub_type": "text",
        "list_items": [
            "$\\textcircled{1}$ 找 line1、line2 和两线的交点 B。（10 分）",
            "$\\textcircled{2}$ 使用模板匹配工具找到凹槽最底点 A。（10 分）",
            "$\\textcircled{3}$ 在 A 点做一条和 line2 平行的线，并得到和 line1 的交点 C。（20 分）",
            "$\\textcircled{4}$ 以 A 为原点，AC 为半径做一个圆。（20 分）"
        ],
        "bbox": [
            102,
            287,
            727,
            416
        ],
        "page_idx": 13
    },
    {
        "type": "image",
        "img_path": "images/a2ae48d2073bcc4cd0dda8cc03d51566dfe21ffde993858b06be6310e358d51a.jpg",
        "image_caption": [],
        "image_footnote": [],
        "bbox": [
            110,
            423,
            384,
            625
        ],
        "page_idx": 13
    },
    {
        "type": "list",
        "sub_type": "text",
        "list_items": [
            "做题步骤： $\\cdot$ 单张图 不需要模板。 Findline 工具抓出来 Line1 Line2，并用 intersection 交点工具求得两个直线的交点B。",
            "$\\cdot$ 可以用模板工具将训练中心手动拖动到角点的最低点。"
        ],
        "bbox": [
            100,
            639,
            914,
            730
        ],
        "page_idx": 13
    },
    {
        "type": "image",
        "img_path": "images/328ff2682882f77bd65e0ee4fee7e63e09c68bab35e1da8b02637622ba5c5491.jpg",
        "image_caption": [],
        "image_footnote": [],
        "bbox": [
            102,
            738,
            129,
            772
        ],
        "page_idx": 13
    },
    {
        "type": "image",
        "img_path": "images/3fabe7c272dd0560c01e45cc2ce7aedcfaaf0a4de2f1ad37edf2b9eea237988d.jpg",
        "image_caption": [],
        "image_footnote": [],
        "bbox": [
            149,
            739,
            163,
            753
        ],
        "page_idx": 13
    },
    {
        "type": "list",
        "sub_type": "text",
        "list_items": [
            "Results.Item[0].GetPose(). TranslationX ",
            "Results.Item[0].GetPose(). TranslationY "
        ],
        "bbox": [
            163,
            740,
            480,
            768
        ],
        "page_idx": 13
    },
    {
        "type": "text",
        "text": "模板工具的这两个终端为A点坐标",
        "bbox": [
            581,
            757,
            889,
            774
        ],
        "page_idx": 13
    },
    {
        "type": "list",
        "sub_type": "text",
        "list_items": [
            "$\\textcircled{3}$ 过点 A 创造一条平行于 line2 的平行线 CogCreateLineParallelTool， 用 intersection 交点工具求line1 和创造的平行线的交点C",
            "$\\cdot$ 先用点点测距工具，求得点AC之间的距离，用创造圆工具以点A为圆心，以AC距离为半径做圆 CreateCircle。"
        ],
        "bbox": [
            100,
            787,
            921,
            915
        ],
        "page_idx": 13
    },
    {
        "type": "text",
        "text": "6.、Vision Tools 上机操作题。 （30 分）",
        "text_level": 1,
        "bbox": [
            65,
            105,
            722,
            135
        ],
        "page_idx": 14
    },
    {
        "type": "text",
        "text": "1、使用加载图片文件，做出如下实操试题。",
        "bbox": [
            67,
            156,
            455,
            175
        ],
        "page_idx": 14
    },
    {
        "type": "list",
        "sub_type": "text",
        "list_items": [
            "$\\textcircled{1}$ 如下图所示：求托盘的中心点坐标。",
            "$\\textcircled{2}$ 求托盘上的 Mark 点到托盘的 2 个边缘的距离 d1，d2。"
        ],
        "bbox": [
            65,
            193,
            571,
            249
        ],
        "page_idx": 14
    },
    {
        "type": "image",
        "img_path": "images/1c9d7801a715b306657e5cc9cfb16106a614a6e084096ed949fa0690821aafb9.jpg",
        "image_caption": [],
        "image_footnote": [],
        "bbox": [
            68,
            256,
            448,
            461
        ],
        "page_idx": 14
    },
    {
        "type": "text",
        "text": "做题步骤： $\\textcircled{1}$ 做模板选用斑点加一个矩形拐角，或者一个斑点加一条直线做模板，先检查每个图模板没问题。",
        "bbox": [
            65,
            472,
            929,
            527
        ],
        "page_idx": 14
    },
    {
        "type": "list",
        "sub_type": "text",
        "list_items": [
            "$\\cdot$ 求中心，",
            "$\\cdot$ 用斑点工具得到斑点的质心 XY或者抓圆工具的圆心 XY 并用点到直线测距工具求得两个距离D1D2"
        ],
        "bbox": [
            65,
            546,
            926,
            637
        ],
        "page_idx": 14
    },
    {
        "type": "text",
        "text": "7.判断有无脏污 ",
        "text_level": 1,
        "bbox": [
            65,
            717,
            329,
            747
        ],
        "page_idx": 14
    },
    {
        "type": "text",
        "text": "二、请用noisydiscs图片结合Histogram和ResultsAnalysis工具判断圆内有无脏污。",
        "bbox": [
            72,
            762,
            759,
            801
        ],
        "page_idx": 14
    },
    {
        "type": "text",
        "text": "做题步骤： $\\cdot$ 多张图但是位置关系没有发生变化，可用模板也可不用模板工具。",
        "bbox": [
            65,
            824,
            766,
            843
        ],
        "page_idx": 14
    },
    {
        "type": "list",
        "sub_type": "text",
        "list_items": [
            "$\\cdot$ 用Histogram工具测量图片中间白色区域的灰度信息。",
            "$\\cdot$ 添加 ResultAnalysis，将 Histogram 工具的灰度平均值或者是标准差值输出给 ResultAnalysis"
        ],
        "bbox": [
            65,
            862,
            929,
            917
        ],
        "page_idx": 14
    },
    {
        "type": "text",
        "text": "工具来判断。",
        "bbox": [
            67,
            65,
            179,
            80
        ],
        "page_idx": 15
    },
    {
        "type": "text",
        "text": "$\\cdot$ ResultAnalysis 工具添加表达式，",
        "bbox": [
            67,
            102,
            379,
            120
        ],
        "page_idx": 15
    },
    {
        "type": "image",
        "img_path": "images/a05c0e4e5bdec1c9bd8ff66cb3f27f10c902cf1679a5bbb292e9ebf53d33bf81.jpg",
        "image_caption": [],
        "image_footnote": [],
        "bbox": [
            72,
            127,
            771,
            332
        ],
        "page_idx": 15
    },
    {
        "type": "text",
        "text": "一、 掩膜",
        "text_level": 1,
        "bbox": [
            67,
            346,
            235,
            376
        ],
        "page_idx": 15
    },
    {
        "type": "list",
        "sub_type": "text",
        "list_items": [
            "1. 抓取图像",
            "2. 调整训练图像和训练区域(只需要框中掩膜露出来的特征就行)"
        ],
        "bbox": [
            65,
            390,
            568,
            424
        ],
        "page_idx": 15
    },
    {
        "type": "text",
        "text": "3. 点开图像掩模编辑器",
        "bbox": [
            67,
            429,
            307,
            454
        ],
        "page_idx": 15
    },
    {
        "type": "image",
        "img_path": "images/f2866b5b156a84ece8d1902093880c3d723cd4709aeb9a0a7202d6f01e52811d.jpg",
        "image_caption": [],
        "image_footnote": [],
        "bbox": [
            102,
            460,
            929,
            688
        ],
        "page_idx": 15
    },
    {
        "type": "text",
        "text": "要的特征给擦除出来。",
        "bbox": [
            102,
            705,
            272,
            720
        ],
        "page_idx": 15
    },
    {
        "type": "text",
        "text": "$\\textcircled{2}$ 另外一种是直接选用工具选择合适的图案来将不需要的地方给掩盖掉。",
        "bbox": [
            102,
            722,
            668,
            739
        ],
        "page_idx": 15
    },
    {
        "type": "list",
        "sub_type": "text",
        "list_items": [
            "4. 点击应用，点确定退出掩膜编辑器",
            "5. 调整训练区域，接着把模板做完"
        ],
        "bbox": [
            65,
            741,
            363,
            775
        ],
        "page_idx": 15
    },
    {
        "type": "image",
        "img_path": "images/77b5da8d42b68b89acc24e76e88435f08150e4d09ec7e690ea3f2f8d80da7384.jpg",
        "image_caption": [],
        "image_footnote": [],
        "bbox": [
            68,
            777,
            236,
            906
        ],
        "page_idx": 15
    },
    {
        "type": "text",
        "text": "二、 建模",
        "text_level": 1,
        "bbox": [
            67,
            67,
            236,
            99
        ],
        "page_idx": 16
    },
    {
        "type": "list",
        "sub_type": "text",
        "list_items": [
            "1. 抓取训练图像",
            "2. 将训练模式由“图像”切换为“带图像的形状模型”，在训练区域与原点界面将区域模式的“像素配对限定！框调整掩膜”修改为“像素配对限定框”，此时建模图标亮起 。",
            "3. 点开建模编辑器： $\\textcircled{1}$ 窗口左侧的一些形状可以添加自己需要的特征，线段、圆、多边形等。然后需要双击添忽略极性加的特征设置正确的极性(当忽略极性时，这个极性可以不选择) 。"
        ],
        "bbox": [
            65,
            112,
            929,
            231
        ],
        "page_idx": 16
    },
    {
        "type": "text",
        "text": "提取形状 提取形状",
        "bbox": [
            312,
            255,
            379,
            269
        ],
        "page_idx": 16
    },
    {
        "type": "text",
        "text": "$\\textcircled{2}$ 也可以选择提取形状 ，在形状提取弹窗内，设定合适的对比度阈值还有周长，即可以自",
        "bbox": [
            102,
            261,
            927,
            279
        ],
        "page_idx": 16
    },
    {
        "type": "text",
        "text": "动提取图案中符合这两个参数的特征，并且自动选好特征的极性。",
        "bbox": [
            65,
            296,
            574,
            313
        ],
        "page_idx": 16
    },
    {
        "type": "text",
        "text": "4.退出建模编辑器，调整训练区域将添加的特征框中。接着把模板做完。",
        "bbox": [
            65,
            316,
            621,
            332
        ],
        "page_idx": 16
    },
    {
        "type": "image",
        "img_path": "images/477c9ebe6a88829b26f2b37e7c6fb1351643b826cdf0caec7e1d293a43212d21.jpg",
        "image_caption": [],
        "image_footnote": [],
        "bbox": [
            102,
            332,
            181,
            399
        ],
        "page_idx": 16
    },
    {
        "type": "text",
        "text": "四、Dataman",
        "text_level": 1,
        "bbox": [
            67,
            71,
            285,
            97
        ],
        "page_idx": 17
    },
    {
        "type": "text",
        "text": "1. IP 设定",
        "text_level": 1,
        "bbox": [
            67,
            191,
            183,
            212
        ],
        "page_idx": 17
    },
    {
        "type": "text",
        "text": "参考相机 IP 配置原则，eg：网口 IP：192.168.123.123，扫码枪 IP：192.168.123.124. 扫码枪 IP 需在软件里设置。",
        "bbox": [
            65,
            256,
            914,
            272
        ],
        "page_idx": 17
    },
    {
        "type": "text",
        "text": "2.打光方式介绍",
        "text_level": 1,
        "bbox": [
            65,
            297,
            260,
            319
        ],
        "page_idx": 17
    },
    {
        "type": "text",
        "text": "DM262扫码枪有四个光源，两个普通光源，两个高亮光源，可以不开光源也可以四个光源自由搭配使用，通过训练(调谐)按钮设置自动调节光源，或者是在扫码枪缩略图位置手动开启关闭扫码枪的光源。",
        "bbox": [
            65,
            362,
            924,
            398
        ],
        "page_idx": 17
    },
    {
        "type": "text",
        "text": "3.数据格式、读码类型介绍",
        "text_level": 1,
        "bbox": [
            65,
            422,
            394,
            444
        ],
        "page_idx": 17
    },
    {
        "type": "text",
        "text": "Symbology Settings(码类型设置)：",
        "bbox": [
            100,
            488,
            354,
            502
        ],
        "page_idx": 17
    },
    {
        "type": "text",
        "text": "General：选择勾选需要解的码的类型",
        "bbox": [
            134,
            506,
            428,
            521
        ],
        "page_idx": 17
    },
    {
        "type": "text",
        "text": "Multicode Settings(多码)： Number of codes 设置允许读取到的码的数量 适用于一幅图里有多个码",
        "bbox": [
            134,
            525,
            882,
            541
        ],
        "page_idx": 17
    },
    {
        "type": "text",
        "text": "allow Partial Results：勾选时可以将解出来的每一个码都输出",
        "bbox": [
            136,
            543,
            608,
            558
        ],
        "page_idx": 17
    },
    {
        "type": "text",
        "text": "4.触发模式的介绍(Singal,Burst,Continue 等模式的使用场景)",
        "text_level": 1,
        "bbox": [
            65,
            602,
            805,
            625
        ],
        "page_idx": 17
    },
    {
        "type": "text",
        "text": "Singal：拍摄单张图片进行解码，每个setup(通道)会拍一张，可以设置单个setup的超时时间",
        "bbox": [
            65,
            668,
            781,
            684
        ],
        "page_idx": 17
    },
    {
        "type": "text",
        "text": "Burst：拍摄一组图片解码，并在首次成功解码时停止解码，我们可以设定每组图片拍摄数量，还有每次拍照的时间间隔，每次拍照都可以设定一个超时时间",
        "bbox": [
            65,
            686,
            924,
            721
        ],
        "page_idx": 17
    },
    {
        "type": "text",
        "text": "Continue：在触发信号结束之前连续拍照，可以设定每次拍照时间间隔",
        "bbox": [
            65,
            724,
            613,
            739
        ],
        "page_idx": 17
    },
    {
        "type": "text",
        "text": "5.PPM值的介绍 ",
        "text_level": 1,
        "bbox": [
            65,
            764,
            268,
            785
        ],
        "page_idx": 17
    },
    {
        "type": "text",
        "text": "含义：码的每个module(模块)的平均像素值 每个模块占了几个像素",
        "bbox": [
            65,
            829,
            601,
            845
        ],
        "page_idx": 17
    },
    {
        "type": "text",
        "text": "意义：它是判断扫码稳定性的一个重要依据，它不是越大越好也不是越小越好，需要控制在一个合理的范围，二维码一般建议在5~8，一维码建议在3以上",
        "bbox": [
            65,
            848,
            914,
            883
        ],
        "page_idx": 17
    },
    {
        "type": "text",
        "text": "6. DataMatrix 码的介绍(Verify 相关标准)",
        "text_level": 1,
        "bbox": [
            67,
            63,
            552,
            86
        ],
        "page_idx": 18
    },
    {
        "type": "text",
        "text": "DataMatrix的组成：静区、L型寻边区、模块或单元、计时图案、数据区 ",
        "bbox": [
            67,
            129,
            628,
            143
        ],
        "page_idx": 18
    },
    {
        "type": "image",
        "img_path": "images/187ff135d70f1d9da7f3cdaf074674604c60e74e3bf904cd9f0753d4a77076a5.jpg",
        "image_caption": [],
        "image_footnote": [],
        "bbox": [
            75,
            147,
            297,
            309
        ],
        "page_idx": 18
    },
    {
        "type": "image",
        "img_path": "images/3a6ac96963ed9cc8eefc9c5f015dc3a0e16f2f6722f7c2dc54d4a17cbc6bf237.jpg",
        "image_caption": [],
        "image_footnote": [],
        "bbox": [
            302,
            156,
            406,
            309
        ],
        "page_idx": 18
    },
    {
        "type": "text",
        "text": "激光镭雕 喷码等方式出来的 DataMatrix 码质量不一，需要专门的仪器检测",
        "bbox": [
            65,
            332,
            640,
            348
        ],
        "page_idx": 18
    },
    {
        "type": "text",
        "text": "Verifier：等级测试仪",
        "bbox": [
            68,
            351,
            230,
            366
        ],
        "page_idx": 18
    },
    {
        "type": "text",
        "text": "等级测试仪是根据ISO15415或AIM DPM等标准来制定的，达到标准就说明这个码具有可读性的，达不到标准就是可能存在读取失败的风险",
        "bbox": [
            65,
            369,
            700,
            403
        ],
        "page_idx": 18
    },
    {
        "type": "text",
        "text": "常见低等级码：L边损坏，对比度不佳，模块化不佳，模块偏离，条码损坏，条码变形eg：喷码机 喷的码需要测定码的质量等级，一般ABCD中 A和B等级为合格",
        "bbox": [
            65,
            406,
            734,
            441
        ],
        "page_idx": 18
    }
]